glimmer/__init__.py
glimmer/api/__init__.py
glimmer/data/default_config.ini
glimmer/libs/__init__.py
glimmer/libs/controller.py
glimmer/libs/core/config.py
glimmer/libs/core/enums.py
glimmer/libs/core/exceptions.py
glimmer/libs/core/loader.py
glimmer/libs/core/parser.py
glimmer/libs/core/plugin.py
glimmer/libs/core/poc.py
glimmer/libs/logger.py
glimmer/libs/request/__init__.py
glimmer/libs/request/patch.py
glimmer/main.py
glimmer/plugins/output/console.py
glimmer/plugins/output/pure_text.py
glimmer/plugins/output/table.py
glimmer/plugins/output/text.py
glimmer/plugins/parser/file.py
glimmer/plugins/parser/fofa.py
glimmer/plugins/parser/python.py
glimmer/plugins/parser/repo.py
glimmer/plugins/parser/shodan.py
glimmer/plugins/parser/url.py
glimmer/plugins/parser/zoomeye.py
glimmer/pocs/_demo/demo.py
glimmer/pocs/_demo/demo2.py
glimmer/thirdparty/__init__.py
glimmer/thirdparty/base64.py
glimmer/thirdparty/click.py
glimmer/thirdparty/parser.py
glimmer/utils/__init__.py
glimmer/utils/cyberspace/__init__.py
glimmer/utils/cyberspace/fofa.py
glimmer/utils/cyberspace/shodan.py
glimmer/utils/cyberspace/utils.py
glimmer/utils/cyberspace/zoomeye.py
glimmer/utils/printer.py
glimmer/utils/utils.py
python_glimmer-1.7.3.dist-info/entry_points.txt
python_glimmer-1.7.3.dist-info/WHEEL
python_glimmer-1.7.3.dist-info/METADATA
python_glimmer-1.7.3.dist-info/RECORD
