Metadata-Version: 2.1
Name: python-glimmer
Version: 1.7.3
Summary: UNKNOWN
License: MIT
Author-email: WAY29 <1162410187@qq.com>
Requires-Python: >=3.6
Classifier: License :: OSI Approved :: MIT License
Classifier: Programming Language :: Python :: 3
Classifier: Programming Language :: Python :: 3.6
Classifier: Programming Language :: Python :: 3.7
Classifier: Programming Language :: Python :: 3.8
Classifier: Programming Language :: Python :: 3.9
Requires-Dist: click~=7.1
Requires-Dist: func-timeout~=4.3
Requires-Dist: requests~=2.25
Requires-Dist: rich~=10.0
Requires-Dist: shodan~=1.25
Requires-Dist: zoomeye~=2.0
Project-URL: homepage, https://github.com/WAY29/glimmer
